vocode_velocity/__init__.py
vocode_velocity/helpers.py
vocode_velocity/logging.py
vocode_velocity/meta.py
vocode_velocity/streaming/action/abstract_factory.py
vocode_velocity/streaming/action/action_utils.py
vocode_velocity/streaming/action/base_action.py
vocode_velocity/streaming/action/default_factory.py
vocode_velocity/streaming/action/dtmf.py
vocode_velocity/streaming/action/end_conversation.py
vocode_velocity/streaming/action/execute_external_action.py
vocode_velocity/streaming/action/external_actions_requester.py
vocode_velocity/streaming/action/phone_call_action.py
vocode_velocity/streaming/action/record_email.py
vocode_velocity/streaming/action/transfer_call.py
vocode_velocity/streaming/action/wait.py
vocode_velocity/streaming/action/worker.py
vocode_velocity/streaming/agent/__init__.py
vocode_velocity/streaming/agent/abstract_factory.py
vocode_velocity/streaming/agent/anthropic_agent.py
vocode_velocity/streaming/agent/anthropic_utils.py
vocode_velocity/streaming/agent/base_agent.py
vocode_velocity/streaming/agent/chat_gpt_agent.py
vocode_velocity/streaming/agent/default_factory.py
vocode_velocity/streaming/agent/echo_agent.py
vocode_velocity/streaming/agent/goodbye.py
vocode_velocity/streaming/agent/gpt4all_agent.py
vocode_velocity/streaming/agent/groq_agent.py
vocode_velocity/streaming/agent/langchain_agent.py
vocode_velocity/streaming/agent/llamacpp_agent.py
vocode_velocity/streaming/agent/openai_utils.py
vocode_velocity/streaming/agent/phrase_trigger.py
vocode_velocity/streaming/agent/restful_user_implemented_agent.py
vocode_velocity/streaming/agent/streaming_utils.py
vocode_velocity/streaming/agent/token_utils.py
vocode_velocity/streaming/agent/vertex_ai_agent.py
vocode_velocity/streaming/agent/websocket_user_implemented_agent.py
vocode_velocity/streaming/client_backend/conversation.py
vocode_velocity/streaming/constants.py
vocode_velocity/streaming/input_device/base_input_device.py
vocode_velocity/streaming/input_device/file_input_device.py
vocode_velocity-0.1.123.dist-info/LICENSE
vocode_velocity-0.1.123.dist-info/METADATA
vocode_velocity-0.1.123.dist-info/WHEEL
vocode_velocity-0.1.123.dist-info/RECORD
