Metadata-Version: 2.1
Name: vocode_velocity
Version: 0.1.123
Summary: The all-in-one voice SDK
Home-page: https://github.com/Velocity-Engineering/vocode-core
License: MIT
Author: Ajay Raj
Author-email: ajay@vocode.dev
Requires-Python: >=3.10,<4.0
Classifier: License :: OSI Approved :: MIT License
Classifier: Programming Language :: Python :: 3
Classifier: Programming Language :: Python :: 3.10
Classifier: Programming Language :: Python :: 3.11
Classifier: Programming Language :: Python :: 3.12
Classifier: Programming Language :: Python :: 3.13
Provides-Extra: all
Provides-Extra: langchain
Provides-Extra: langchain-extras
Provides-Extra: synthesizers
Provides-Extra: telephony
Provides-Extra: transcribers
Requires-Dist: aiohttp (>=3.9.5,<4.0.0)
Requires-Dist: anthropic (>=0.28.0,<0.29.0)
Requires-Dist: azure-cognitiveservices-speech (>=1.38.0,<2.0.0)
Requires-Dist: cartesia (>=1.1.0,<2.0.0) ; extra == "synthesizers" or extra == "all"
Requires-Dist: elevenlabs (>=1.2.2,<2.0.0)
Requires-Dist: fastapi (>=0.111.0,<0.112.0)
Requires-Dist: google-cloud-speech (>=2.26.0,<3.0.0) ; extra == "transcribers" or extra == "all"
Requires-Dist: google-cloud-texttospeech (>=2.16.3,<3.0.0) ; extra == "synthesizers" or extra == "all"
Requires-Dist: groq (>=0.9.0,<0.10.0) ; extra == "all"
Requires-Dist: janus (>=1.0.0,<2.0.0)
Requires-Dist: jinja2 (>=3.1.4,<4.0.0)
Requires-Dist: jsonschema (>=4.22.0,<5.0.0)
Requires-Dist: langchain (>=0.2.3,<0.3.0) ; extra == "langchain" or extra == "all"
Requires-Dist: langchain-anthropic (>=0.1.15,<0.2.0) ; extra == "langchain-extras" or extra == "all"
Requires-Dist: langchain-community (>=0.2.4,<0.3.0) ; extra == "langchain" or extra == "all"
Requires-Dist: langchain-google-vertexai (>=1.0.5,<2.0.0) ; extra == "langchain-extras" or extra == "all"
Requires-Dist: langchain-openai (>=0.1.8,<0.2.0) ; extra == "langchain-extras" or extra == "all"
Requires-Dist: livekit (>=0.11.1,<0.12.0) ; extra == "all"
Requires-Dist: loguru (>=0.7.2,<0.8.0)
Requires-Dist: miniaudio (>=1.59.0,<2.0.0)
Requires-Dist: nltk (>=3.8.1,<4.0.0)
Requires-Dist: numpy (>=1.26.4,<2.0.0)
Requires-Dist: openai (>=1.30.5,<2.0.0)
Requires-Dist: opentelemetry-sdk (>=1.24.0,<2.0.0)
Requires-Dist: phonenumbers (>=8.13.37,<9.0.0)
Requires-Dist: pvkoala (>=2.0.1,<3.0.0) ; extra == "synthesizers" or extra == "all"
Requires-Dist: pydantic (>=2.7.2,<3.0.0)
Requires-Dist: pydantic-settings (>=2.3.0,<3.0.0)
Requires-Dist: pydub (>=0.25.1,<0.26.0)
Requires-Dist: pyht (>=0.0.28,<0.0.29)
Requires-Dist: redis (>=5.0.4,<6.0.0)
Requires-Dist: requests (>=2.32.3,<3.0.0)
Requires-Dist: sentry-sdk[fastapi] (>=2.3.1,<3.0.0)
Requires-Dist: sounddevice (>=0.4.7,<0.5.0)
Requires-Dist: tiktoken (>=0.7.0,<0.8.0)
Requires-Dist: twilio (>=9.1.0,<10.0.0) ; extra == "telephony" or extra == "all"
Requires-Dist: uvicorn (>=0.30.0,<0.31.0)
Requires-Dist: vonage (>=3.14.0,<4.0.0) ; extra == "telephony" or extra == "all"
Requires-Dist: websockets (>=14.1,<15.0)
